mujoco_ar/__init__.py
mujoco_ar/connector.py
mujoco_controller/__init__.py
mujoco_controller/connector.py
mujoco_controller-0.4.0.dist-info/METADATA
mujoco_controller-0.4.0.dist-info/WHEEL
mujoco_controller-0.4.0.dist-info/top_level.txt
mujoco_controller-0.4.0.dist-info/RECORD
