Metadata-Version: 2.1
Name: mujoco_controller
Version: 0.4.0
Summary: A connector to receive position and rotation data from a connected application.
Home-page: https://github.com/yourusername/mujocoar
Author: Omar Rayyan
Author-email: olr7742@nyu.edu
License: MIT
Classifier: Programming Language :: Python :: 3
Classifier: License :: OSI Approved :: MIT License
Classifier: Operating System :: OS Independent
Requires-Python: >=3.6
Requires-Dist: asyncio
Requires-Dist: websockets
Requires-Dist: numpy
Requires-Dist: psutil
Requires-Dist: opencv-python
Requires-Dist: mujoco
